segy/__init__.py
segy/accessors.py
segy/alias/__init__.py
segy/alias/core.py
segy/alias/segyio.py
segy/alias/seis_unix.py
segy/arrays.py
segy/cli/__init__.py
segy/cli/common.py
segy/cli/dump.py
segy/cli/segy.py
segy/config.py
segy/constants.py
segy/ebcdic.py
segy/exceptions.py
segy/factory.py
segy/file.py
segy/ibm.py
segy/indexing.py
segy/inference.py
segy/py.typed
segy/schema/__init__.py
segy/schema/base.py
segy/schema/format.py
segy/schema/header.py
segy/schema/segy.py
segy/schema/text_header.py
segy/schema/trace.py
segy/standards/__init__.py
segy/standards/codes.py
segy/standards/fields/__init__.py
segy/standards/fields/base.py
segy/standards/fields/binary.py
segy/standards/fields/trace.py
segy/standards/minimal.py
segy/standards/registry.py
segy/standards/spec.py
segy/transforms.py
segy-0.5.3.dist-info/licenses/LICENSE
segy-0.5.3.dist-info/WHEEL
segy-0.5.3.dist-info/entry_points.txt
segy-0.5.3.dist-info/METADATA
segy-0.5.3.dist-info/RECORD
