Metadata-Version: 2.4
Name: segy
Version: 0.5.3
Summary: The Ultimate Python SEG-Y I/O with Cloud Support and Schemas
Keywords: segy,seismic,data,geophysics
Author: Altay Sansal
Author-email: Altay Sansal <altay.sansal@tgs.com>
License-Expression: Apache-2.0
License-File: LICENSE
Classifier: Programming Language :: Python :: 3
Classifier: Programming Language :: Python :: 3.11
Classifier: Programming Language :: Python :: 3.12
Classifier: Programming Language :: Python :: 3.13
Classifier: License :: OSI Approved :: Apache Software License
Classifier: Development Status :: 4 - Beta
Requires-Dist: fsspec>=2024.10.0
Requires-Dist: numpy>=2.3.0,<3.0.0
Requires-Dist: pydantic>=2.9.2,<3.0.0
Requires-Dist: pydantic-settings>=2.6.1,<3.0.0
Requires-Dist: numba>=0.62.0,<0.70.0
Requires-Dist: pandas>=2.2.2,<3.0.0
Requires-Dist: typer>=0.18.0,<1.0.0
Requires-Dist: rapidfuzz>=3.10.1,<4.0.0
Requires-Dist: s3fs>=2024.10.0 ; extra == 'cloud'
Requires-Dist: gcsfs>=2024.10.0 ; extra == 'cloud'
Requires-Dist: adlfs>=2024.7.0 ; extra == 'cloud'
Requires-Python: >=3.11, <3.14
Project-URL: documentation, https://segy.readthedocs.io
Project-URL: repository, https://github.com/TGSAI/segy
Provides-Extra: cloud
